[
  {
    "round": 1,
    "new_model_price": 53.07453155517578,
    "g_model_loss": 4.718003273010254,
    "submits": [
      {
        "walletId": "wallet_0",
        "loss": 3.591413736343384,
        "delta_local_loss": 0,
        "delta_gap": 1.4340426921844482,
        "contribution": 1.4340426921844482,
        "reward": 67.6160129615926
      },
      {
        "walletId": "wallet_1",
        "loss": 3.638874053955078,
        "delta_local_loss": 0,
        "delta_gap": 1.386582374572754,
        "contribution": 1.386582374572754,
        "reward": 66.11926462967558
      },
      {
        "walletId": "wallet_2",
        "loss": 3.163079023361206,
        "delta_local_loss": 0,
        "delta_gap": 1.862377405166626,
        "contribution": 1.862377405166626,
        "reward": 79.93734950817932
      },
      {
        "walletId": "wallet_3",
        "loss": 2.912043809890747,
        "delta_local_loss": 0,
        "delta_gap": 2.113412618637085,
        "contribution": 2.113412618637085,
        "reward": 86.32737290055249
      }
    ]
  },
  {
    "round": 2,
    "new_model_price": 74.35416221618652,
    "g_model_loss": 2.5900402069091797,
    "submits": [
      {
        "walletId": "wallet_0",
        "loss": 2.7531116008758545,
        "delta_local_loss": 0.8383021354675293,
        "delta_gap": 1.9648916721343994,
        "contribution": 1.4015969038009644,
        "reward": 73.24074875517572
      },
      {
        "walletId": "wallet_1",
        "loss": 2.4893877506256104,
        "delta_local_loss": 1.1494863033294678,
        "delta_gap": 2.2286155223846436,
        "contribution": 1.6890509128570557,
        "reward": 82.6915761997786
      },
      {
        "walletId": "wallet_2",
        "loss": 2.644043445587158,
        "delta_local_loss": 0.5190355777740479,
        "delta_gap": 2.0739598274230957,
        "contribution": 1.2964977025985718,
        "reward": 69.49996666902777
      },
      {
        "walletId": "wallet_3",
        "loss": 2.375000476837158,
        "delta_local_loss": 0.5370433330535889,
        "delta_gap": 2.3430027961730957,
        "contribution": 1.4400230646133423,
        "reward": 74.56770837601792
      }
    ]
  },
  {
    "round": 3,
    "new_model_price": 81.2181568145752,
    "g_model_loss": 1.9036407470703125,
    "submits": [
      {
        "walletId": "wallet_0",
        "loss": 2.2714436054229736,
        "delta_local_loss": 0.48166799545288086,
        "delta_gap": 0.31859660148620605,
        "contribution": 0.40013229846954346,
        "reward": 80.51855452769524
      },
      {
        "walletId": "wallet_1",
        "loss": 2.1014692783355713,
        "delta_local_loss": 0.38791847229003906,
        "delta_gap": 0.4885709285736084,
        "contribution": 0.43824470043182373,
        "reward": 86.94361360373789
      },
      {
        "walletId": "wallet_2",
        "loss": 2.244645833969116,
        "delta_local_loss": 0.399397611618042,
        "delta_gap": 0.3453943729400635,
        "contribution": 0.37239599227905273,
        "reward": 75.73179174067883
      },
      {
        "walletId": "wallet_3",
        "loss": 2.214510440826416,
        "delta_local_loss": 0.1604900360107422,
        "delta_gap": 0.37552976608276367,
        "contribution": 0.26800990104675293,
        "reward": 56.806040127888025
      }
    ]
  },
  {
    "round": 4,
    "new_model_price": 83.70005965232849,
    "g_model_loss": 1.655450463294983,
    "submits": [
      {
        "walletId": "wallet_0",
        "loss": 1.9791711568832397,
        "delta_local_loss": 0.2922724485397339,
        "delta_gap": -0.07553040981292725,
        "contribution": 0.10837101936340332,
        "reward": 40.403364625486226
      },
      {
        "walletId": "wallet_1",
        "loss": 1.8498510122299194,
        "delta_local_loss": 0.25161826610565186,
        "delta_gap": 0.053789734840393066,
        "contribution": 0.15270400047302246,
        "reward": 55.80391109594524
      },
      {
        "walletId": "wallet_2",
        "loss": 1.809827208518982,
        "delta_local_loss": 0.4348186254501343,
        "delta_gap": 0.09381353855133057,
        "contribution": 0.2643160820007324,
        "reward": 92.09570465000027
      },
      {
        "walletId": "wallet_3",
        "loss": 1.7300472259521484,
        "delta_local_loss": 0.4844632148742676,
        "delta_gap": 0.17359352111816406,
        "contribution": 0.3290283679962158,
        "reward": 111.69701962856828
      }
    ]
  },
  {
    "round": 5,
    "new_model_price": 84.7416877746582,
    "g_model_loss": 1.5512876510620117,
    "submits": [
      {
        "walletId": "wallet_0",
        "loss": 1.8911010026931763,
        "delta_local_loss": 0.08807015419006348,
        "delta_gap": -0.23565053939819336,
        "contribution": 0,
        "reward": 0.0
      },
      {
        "walletId": "wallet_1",
        "loss": 1.7489492893218994,
        "delta_local_loss": 0.10090172290802002,
        "delta_gap": -0.0934988260269165,
        "contribution": 0.003701448440551758,
        "reward": 23.698218961970323
      },
      {
        "walletId": "wallet_2",
        "loss": 1.730264663696289,
        "delta_local_loss": 0.07956254482269287,
        "delta_gap": -0.07481420040130615,
        "contribution": 0.0023741722106933594,
        "reward": 15.210507610652824
      },
      {
        "walletId": "wallet_3",
        "loss": 1.651204228401184,
        "delta_local_loss": 0.07884299755096436,
        "delta_gap": 0.004246234893798828,
        "contribution": 0.04154461622238159,
        "reward": 261.09127342737685
      }
    ]
  },
  {
    "round": 6,
    "new_model_price": 85.29117107391357,
    "g_model_loss": 1.4963393211364746,
    "submits": [
      {
        "walletId": "wallet_0",
        "loss": 1.8359383344650269,
        "delta_local_loss": 0.055162668228149414,
        "delta_gap": -0.28465068340301514,
        "contribution": 0,
        "reward": 75.0
      },
      {
        "walletId": "wallet_1",
        "loss": 1.701275110244751,
        "delta_local_loss": 0.04767417907714844,
        "delta_gap": -0.14998745918273926,
        "contribution": 0,
        "reward": 75.0
      },
      {
        "walletId": "wallet_2",
        "loss": 1.7388684749603271,
        "delta_local_loss": -0.008603811264038086,
        "delta_gap": -0.18758082389831543,
        "contribution": 0,
        "reward": 75.0
      },
      {
        "walletId": "wallet_3",
        "loss": 1.6591298580169678,
        "delta_local_loss": -0.007925629615783691,
        "delta_gap": -0.10784220695495605,
        "contribution": 0,
        "reward": 75.0
      }
    ]
  },
  {
    "round": 7,
    "new_model_price": 85.30800342559814,
    "g_model_loss": 1.4946560859680176,
    "submits": [
      {
        "walletId": "wallet_0",
        "loss": 1.8560549020767212,
        "delta_local_loss": -0.020116567611694336,
        "delta_gap": -0.3597155809402466,
        "contribution": 0,
        "reward": 75.0
      },
      {
        "walletId": "wallet_1",
        "loss": 1.6855173110961914,
        "delta_local_loss": 0.01575779914855957,
        "delta_gap": -0.1891779899597168,
        "contribution": 0,
        "reward": 75.0
      },
      {
        "walletId": "wallet_2",
        "loss": 1.679965853691101,
        "delta_local_loss": 0.058902621269226074,
        "delta_gap": -0.18362653255462646,
        "contribution": 0,
        "reward": 75.0
      },
      {
        "walletId": "wallet_3",
        "loss": 1.7631391286849976,
        "delta_local_loss": -0.10400927066802979,
        "delta_gap": -0.26679980754852295,
        "contribution": 0,
        "reward": 75.0
      }
    ]
  },
  {
    "round": 8,
    "new_model_price": 85.39821863174438,
    "g_model_loss": 1.4856345653533936,
    "submits": [
      {
        "walletId": "wallet_0",
        "loss": 1.8273775577545166,
        "delta_local_loss": 0.02867734432220459,
        "delta_gap": -0.332721471786499,
        "contribution": 0,
        "reward": 75.0
      },
      {
        "walletId": "wallet_1",
        "loss": 1.7433196306228638,
        "delta_local_loss": -0.05780231952667236,
        "delta_gap": -0.2486635446548462,
        "contribution": 0,
        "reward": 75.0
      },
      {
        "walletId": "wallet_2",
        "loss": 1.690714955329895,
        "delta_local_loss": -0.010749101638793945,
        "delta_gap": -0.19605886936187744,
        "contribution": 0,
        "reward": 75.0
      },
      {
        "walletId": "wallet_3",
        "loss": 1.663983702659607,
        "delta_local_loss": 0.09915542602539062,
        "delta_gap": -0.16932761669158936,
        "contribution": 0,
        "reward": 75.0
      }
    ]
  },
  {
    "round": 9,
    "new_model_price": 85.5871319770813,
    "g_model_loss": 1.4667432308197021,
    "submits": [
      {
        "walletId": "wallet_0",
        "loss": 1.8427587747573853,
        "delta_local_loss": -0.015381217002868652,
        "delta_gap": -0.3571242094039917,
        "contribution": 0,
        "reward": 75.0
      },
      {
        "walletId": "wallet_1",
        "loss": 1.7611966133117676,
        "delta_local_loss": -0.01787698268890381,
        "delta_gap": -0.275562047958374,
        "contribution": 0,
        "reward": 75.0
      },
      {
        "walletId": "wallet_2",
        "loss": 1.6803467273712158,
        "delta_local_loss": 0.0103682279586792,
        "delta_gap": -0.19471216201782227,
        "contribution": 0,
        "reward": 75.0
      },
      {
        "walletId": "wallet_3",
        "loss": 1.6423697471618652,
        "delta_local_loss": 0.0216139554977417,
        "delta_gap": -0.15673518180847168,
        "contribution": 0,
        "reward": 75.0
      }
    ]
  },
  {
    "round": 10,
    "new_model_price": 85.37205100059509,
    "g_model_loss": 1.4882513284683228,
    "submits": [
      {
        "walletId": "wallet_0",
        "loss": 1.916980504989624,
        "delta_local_loss": -0.07422173023223877,
        "delta_gap": -0.4502372741699219,
        "contribution": 0,
        "reward": 75.0
      },
      {
        "walletId": "wallet_1",
        "loss": 1.7681994438171387,
        "delta_local_loss": -0.007002830505371094,
        "delta_gap": -0.3014562129974365,
        "contribution": 0,
        "reward": 75.0
      },
      {
        "walletId": "wallet_2",
        "loss": 1.724336862564087,
        "delta_local_loss": -0.043990135192871094,
        "delta_gap": -0.25759363174438477,
        "contribution": 0,
        "reward": 75.0
      },
      {
        "walletId": "wallet_3",
        "loss": 1.7103832960128784,
        "delta_local_loss": -0.06801354885101318,
        "delta_gap": -0.24364006519317627,
        "contribution": 0,
        "reward": 75.0
      }
    ]
  },
  {
    "round": 11,
    "new_model_price": 85.49087524414062,
    "g_model_loss": 1.4763689041137695,
    "submits": [
      {
        "walletId": "wallet_0",
        "loss": 1.8652477264404297,
        "delta_local_loss": 0.051732778549194336,
        "delta_gap": -0.37699639797210693,
        "contribution": 0,
        "reward": 75.0
      },
      {
        "walletId": "wallet_1",
        "loss": 1.7725636959075928,
        "delta_local_loss": -0.0043642520904541016,
        "delta_gap": -0.28431236743927,
        "contribution": 0,
        "reward": 75.0
      },
      {
        "walletId": "wallet_2",
        "loss": 1.7158269882202148,
        "delta_local_loss": 0.00850987434387207,
        "delta_gap": -0.2275756597518921,
        "contribution": 0,
        "reward": 75.0
      },
      {
        "walletId": "wallet_3",
        "loss": 1.6631131172180176,
        "delta_local_loss": 0.04727017879486084,
        "delta_gap": -0.17486178874969482,
        "contribution": 0,
        "reward": 75.0
      }
    ]
  },
  {
    "round": 12,
    "new_model_price": 85.38683891296387,
    "g_model_loss": 1.4867725372314453,
    "submits": [
      {
        "walletId": "wallet_0",
        "loss": 1.9256854057312012,
        "delta_local_loss": -0.060437679290771484,
        "delta_gap": -0.44931650161743164,
        "contribution": 0,
        "reward": 75.0
      },
      {
        "walletId": "wallet_1",
        "loss": 1.7944704294204712,
        "delta_local_loss": -0.021906733512878418,
        "delta_gap": -0.31810152530670166,
        "contribution": 0,
        "reward": 75.0
      },
      {
        "walletId": "wallet_2",
        "loss": 1.743668794631958,
        "delta_local_loss": -0.027841806411743164,
        "delta_gap": -0.2672998905181885,
        "contribution": 0,
        "reward": 75.0
      },
      {
        "walletId": "wallet_3",
        "loss": 1.8229950666427612,
        "delta_local_loss": -0.15988194942474365,
        "delta_gap": -0.3466261625289917,
        "contribution": 0,
        "reward": 75.0
      }
    ]
  },
  {
    "round": 13,
    "new_model_price": 85.07428526878357,
    "g_model_loss": 1.518027901649475,
    "submits": [
      {
        "walletId": "wallet_0",
        "loss": 1.9312677383422852,
        "delta_local_loss": -0.005582332611083984,
        "delta_gap": -0.44449520111083984,
        "contribution": 0,
        "reward": 75.0
      },
      {
        "walletId": "wallet_1",
        "loss": 1.9381427764892578,
        "delta_local_loss": -0.14367234706878662,
        "delta_gap": -0.4513702392578125,
        "contribution": 0,
        "reward": 75.0
      },
      {
        "walletId": "wallet_2",
        "loss": 1.764662504196167,
        "delta_local_loss": -0.020993709564208984,
        "delta_gap": -0.2778899669647217,
        "contribution": 0,
        "reward": 75.0
      },
      {
        "walletId": "wallet_3",
        "loss": 1.7046023607254028,
        "delta_local_loss": 0.1183927059173584,
        "delta_gap": -0.21782982349395752,
        "contribution": 0,
        "reward": 75.0
      }
    ]
  },
  {
    "round": 14,
    "new_model_price": 85.03275394439697,
    "g_model_loss": 1.5221810340881348,
    "submits": [
      {
        "walletId": "wallet_0",
        "loss": 2.0672383308410645,
        "delta_local_loss": -0.1359705924987793,
        "delta_gap": -0.5492104291915894,
        "contribution": 0,
        "reward": 75.0
      },
      {
        "walletId": "wallet_1",
        "loss": 1.873604416847229,
        "delta_local_loss": 0.06453835964202881,
        "delta_gap": -0.3555765151977539,
        "contribution": 0,
        "reward": 75.0
      },
      {
        "walletId": "wallet_2",
        "loss": 1.8446319103240967,
        "delta_local_loss": -0.07996940612792969,
        "delta_gap": -0.3266040086746216,
        "contribution": 0,
        "reward": 75.0
      },
      {
        "walletId": "wallet_3",
        "loss": 1.747572898864746,
        "delta_local_loss": -0.04297053813934326,
        "delta_gap": -0.229544997215271,
        "contribution": 0,
        "reward": 75.0
      }
    ]
  },
  {
    "round": 15,
    "new_model_price": 84.84077215194702,
    "g_model_loss": 1.5413792133331299,
    "submits": [
      {
        "walletId": "wallet_0",
        "loss": 2.0577657222747803,
        "delta_local_loss": 0.00947260856628418,
        "delta_gap": -0.5355846881866455,
        "contribution": 0,
        "reward": 75.0
      },
      {
        "walletId": "wallet_1",
        "loss": 2.005207061767578,
        "delta_local_loss": -0.13160264492034912,
        "delta_gap": -0.48302602767944336,
        "contribution": 0,
        "reward": 75.0
      },
      {
        "walletId": "wallet_2",
        "loss": 1.8421530723571777,
        "delta_local_loss": 0.0024788379669189453,
        "delta_gap": -0.31997203826904297,
        "contribution": 0,
        "reward": 75.0
      },
      {
        "walletId": "wallet_3",
        "loss": 1.7281110286712646,
        "delta_local_loss": 0.019461870193481445,
        "delta_gap": -0.20592999458312988,
        "contribution": 0,
        "reward": 75.0
      }
    ]
  },
  {
    "round": 16,
    "new_model_price": 84.75752472877502,
    "g_model_loss": 1.5497039556503296,
    "submits": [
      {
        "walletId": "wallet_0",
        "loss": 1.9965250492095947,
        "delta_local_loss": 0.06124067306518555,
        "delta_gap": -0.45514583587646484,
        "contribution": 0,
        "reward": 75.0
      },
      {
        "walletId": "wallet_1",
        "loss": 1.9833450317382812,
        "delta_local_loss": 0.021862030029296875,
        "delta_gap": -0.44196581840515137,
        "contribution": 0,
        "reward": 75.0
      },
      {
        "walletId": "wallet_2",
        "loss": 1.8991906642913818,
        "delta_local_loss": -0.0570375919342041,
        "delta_gap": -0.35781145095825195,
        "contribution": 0,
        "reward": 75.0
      },
      {
        "walletId": "wallet_3",
        "loss": 1.7642700672149658,
        "delta_local_loss": -0.03615903854370117,
        "delta_gap": -0.22289085388183594,
        "contribution": 0,
        "reward": 75.0
      }
    ]
  },
  {
    "round": 17,
    "new_model_price": 84.52539324760437,
    "g_model_loss": 1.572917103767395,
    "submits": [
      {
        "walletId": "wallet_0",
        "loss": 2.035503625869751,
        "delta_local_loss": -0.03897857666015625,
        "delta_gap": -0.4857996702194214,
        "contribution": 0,
        "reward": 75.0
      },
      {
        "walletId": "wallet_1",
        "loss": 2.026754856109619,
        "delta_local_loss": -0.04340982437133789,
        "delta_gap": -0.47705090045928955,
        "contribution": 0,
        "reward": 75.0
      },
      {
        "walletId": "wallet_2",
        "loss": 1.9603644609451294,
        "delta_local_loss": -0.06117379665374756,
        "delta_gap": -0.4106605052947998,
        "contribution": 0,
        "reward": 75.0
      },
      {
        "walletId": "wallet_3",
        "loss": 1.794848918914795,
        "delta_local_loss": -0.0305788516998291,
        "delta_gap": -0.24514496326446533,
        "contribution": 0,
        "reward": 75.0
      }
    ]
  },
  {
    "round": 18,
    "new_model_price": 84.36584234237671,
    "g_model_loss": 1.5888721942901611,
    "submits": [
      {
        "walletId": "wallet_0",
        "loss": 2.1064326763153076,
        "delta_local_loss": -0.07092905044555664,
        "delta_gap": -0.5335155725479126,
        "contribution": 0,
        "reward": 75.0
      },
      {
        "walletId": "wallet_1",
        "loss": 2.1039345264434814,
        "delta_local_loss": -0.0771796703338623,
        "delta_gap": -0.5310174226760864,
        "contribution": 0,
        "reward": 75.0
      },
      {
        "walletId": "wallet_2",
        "loss": 1.9349472522735596,
        "delta_local_loss": 0.025417208671569824,
        "delta_gap": -0.36203014850616455,
        "contribution": 0,
        "reward": 75.0
      },
      {
        "walletId": "wallet_3",
        "loss": 1.8515231609344482,
        "delta_local_loss": -0.05667424201965332,
        "delta_gap": -0.2786060571670532,
        "contribution": 0,
        "reward": 75.0
      }
    ]
  },
  {
    "round": 19,
    "new_model_price": 84.09547924995422,
    "g_model_loss": 1.6159085035324097,
    "submits": [
      {
        "walletId": "wallet_0",
        "loss": 2.241403102874756,
        "delta_local_loss": -0.13497042655944824,
        "delta_gap": -0.6525309085845947,
        "contribution": 0,
        "reward": 75.0
      },
      {
        "walletId": "wallet_1",
        "loss": 2.0124731063842773,
        "delta_local_loss": 0.0914614200592041,
        "delta_gap": -0.4236009120941162,
        "contribution": 0,
        "reward": 75.0
      },
      {
        "walletId": "wallet_2",
        "loss": 2.071620464324951,
        "delta_local_loss": -0.1366732120513916,
        "delta_gap": -0.48274827003479004,
        "contribution": 0,
        "reward": 75.0
      },
      {
        "walletId": "wallet_3",
        "loss": 1.855249285697937,
        "delta_local_loss": -0.0037261247634887695,
        "delta_gap": -0.2663770914077759,
        "contribution": 0,
        "reward": 75.0
      }
    ]
  },
  {
    "round": 20,
    "new_model_price": 84.1692852973938,
    "g_model_loss": 1.6085278987884521,
    "submits": [
      {
        "walletId": "wallet_0",
        "loss": 2.071106433868408,
        "delta_local_loss": 0.17029666900634766,
        "delta_gap": -0.45519793033599854,
        "contribution": 0,
        "reward": 75.0
      },
      {
        "walletId": "wallet_1",
        "loss": 2.164506196975708,
        "delta_local_loss": -0.15203309059143066,
        "delta_gap": -0.5485976934432983,
        "contribution": 0,
        "reward": 75.0
      },
      {
        "walletId": "wallet_2",
        "loss": 1.946203589439392,
        "delta_local_loss": 0.12541687488555908,
        "delta_gap": -0.3302950859069824,
        "contribution": 0,
        "reward": 75.0
      },
      {
        "walletId": "wallet_3",
        "loss": 1.9135358333587646,
        "delta_local_loss": -0.05828654766082764,
        "delta_gap": -0.297627329826355,
        "contribution": 0,
        "reward": 75.0
      }
    ]
  }
]